pron_difficulty/__init__.py
pron_difficulty/evaluator.py
pron_difficulty/utils/__init__.py
pron_difficulty/utils/phoneme_utils.py
pron_difficulty/utils/phonological_features.py
pron_difficulty-0.2.0.dist-info/METADATA
pron_difficulty-0.2.0.dist-info/WHEEL
pron_difficulty-0.2.0.dist-info/licenses/LICENSE
pron_difficulty-0.2.0.dist-info/RECORD
