Metadata-Version: 2.3
Name: pron_difficulty
Version: 0.2.0
Summary: A package to evaluate pronunciation difficulty of words in multiple languages
Project-URL: Homepage, https://github.com/federicotorrielli/pron-difficulty
Project-URL: Repository, https://github.com/federicotorrielli/pron-difficulty.git
Author-email: Federico Torrielli <federico.torrielli@unito.it>
License: MIT
Keywords: difficulty,multilingual,nlp,pronunciation
Classifier: Development Status :: 3 - Alpha
Classifier: Intended Audience :: Developers
Classifier: License :: OSI Approved :: MIT License
Classifier: Programming Language :: Python :: 3
Classifier: Programming Language :: Python :: 3.8
Classifier: Programming Language :: Python :: 3.9
Classifier: Programming Language :: Python :: 3.10
Classifier: Programming Language :: Python :: 3.11
Classifier: Programming Language :: Python :: 3.12
Requires-Python: >=3.8
Requires-Dist: numpy>=2.1.3
Requires-Dist: phonemizer>=3.3.0
